cfs3/__init__.py
cfs3/cfchunking.py
cfs3/cftools.py
cfs3/drs_view.py
cfs3/logging_utils.py
cfs3/p5inspect.py
cfs3/s3cache.py
cfs3/s3cmd.py
cfs3/s3core.py
cfs3/s3sci.py
cfs3/s3up.py
cfs3/s3view.py
cfs3/skin.py
cfs3-0.2.2.dist-info/licenses/LICENSE.txt
cfs3-0.2.2.dist-info/METADATA
cfs3-0.2.2.dist-info/WHEEL
cfs3-0.2.2.dist-info/entry_points.txt
cfs3-0.2.2.dist-info/top_level.txt
cfs3-0.2.2.dist-info/RECORD
