Metadata-Version: 2.4
Name: cfs3
Version: 0.2.2
Summary: Lightweight tool for investigating data files in an s3 repository
Author-email: Bryan Lawrence <bryan.lawrence@ncas.ac.uk>
License-Expression: BSD-3-Clause
Classifier: Environment :: Console
Classifier: Intended Audience :: Science/Research
Classifier: Natural Language :: English
Classifier: Operating System :: POSIX :: Linux
Classifier: Programming Language :: Python :: 3
Classifier: Programming Language :: Python :: 3.11
Classifier: Programming Language :: Python :: 3.12
Classifier: Programming Language :: Python :: 3.13
Classifier: Programming Language :: Python :: 3.14
Classifier: Topic :: Scientific/Engineering :: Atmospheric Science
Requires-Python: >=3.10
License-File: LICENSE.txt
Requires-Dist: bitmath
Requires-Dist: cf-python
Requires-Dist: cmd2>2
Requires-Dist: fsspec
Requires-Dist: minio
Requires-Dist: pyfive
Requires-Dist: pyreadline3; platform_system == "Windows"
Provides-Extra: test
Requires-Dist: docker; extra == "test"
Requires-Dist: pytest; extra == "test"
Requires-Dist: pytest-metadata; extra == "test"
Requires-Dist: pytest-mock; extra == "test"
Requires-Dist: pytest-xdist; extra == "test"
Provides-Extra: dev
Requires-Dist: pytest; extra == "dev"
Requires-Dist: pytest-mock; extra == "dev"
Requires-Dist: ipython; extra == "dev"
Provides-Extra: doc
Requires-Dist: autodocsumm; extra == "doc"
Requires-Dist: sphinx; extra == "doc"
Requires-Dist: sphinx_rtd_theme; extra == "doc"
Dynamic: license-file
